streamlit_sentence_selector/__init__.py
streamlit_sentence_selector/frontend/build/asset-manifest.json
streamlit_sentence_selector/frontend/build/bootstrap.min.css
streamlit_sentence_selector/frontend/build/index.html
streamlit_sentence_selector/frontend/build/precache-manifest.3632240affd7036174d21e8e1e63093c.js
streamlit_sentence_selector/frontend/build/service-worker.js
streamlit_sentence_selector/frontend/build/static/js/2.484de6c0.chunk.js
streamlit_sentence_selector/frontend/build/static/js/2.484de6c0.chunk.js.LICENSE.txt
streamlit_sentence_selector/frontend/build/static/js/2.484de6c0.chunk.js.map
streamlit_sentence_selector/frontend/build/static/js/main.fa687adc.chunk.js
streamlit_sentence_selector/frontend/build/static/js/main.fa687adc.chunk.js.map
streamlit_sentence_selector/frontend/build/static/js/runtime-main.9807cc7e.js
streamlit_sentence_selector/frontend/build/static/js/runtime-main.9807cc7e.js.map
streamlit_sentence_selector-0.0.10.dist-info/LICENSE
streamlit_sentence_selector-0.0.10.dist-info/METADATA
streamlit_sentence_selector-0.0.10.dist-info/WHEEL
streamlit_sentence_selector-0.0.10.dist-info/top_level.txt
streamlit_sentence_selector-0.0.10.dist-info/RECORD
